wayback_google_analytics/__init__.py
wayback_google_analytics/async_utils.py
wayback_google_analytics/codes.py
wayback_google_analytics/main.py
wayback_google_analytics/output.py
wayback_google_analytics/scraper.py
wayback_google_analytics/utils.py
wayback_google_analytics-0.2.3.dist-info/LICENSE
wayback_google_analytics-0.2.3.dist-info/METADATA
wayback_google_analytics-0.2.3.dist-info/WHEEL
wayback_google_analytics-0.2.3.dist-info/entry_points.txt
wayback_google_analytics-0.2.3.dist-info/RECORD
