Metadata-Version: 2.1
Name: wayback-google-analytics
Version: 0.2.3
Summary: A tool for gathering current and historic google analytics ids from multiple websites
License: MIT
Author: Justin Clark
Author-email: jclarksummit@gmail.com
Requires-Python: >=3.9,<3.13
Classifier: License :: OSI Approved :: MIT License
Classifier: Programming Language :: Python :: 3
Classifier: Programming Language :: Python :: 3.9
Classifier: Programming Language :: Python :: 3.10
Classifier: Programming Language :: Python :: 3.11
Classifier: Programming Language :: Python :: 3.12
Requires-Dist: aiohttp (==3.8.5)
Requires-Dist: aiosignal (==1.3.1)
Requires-Dist: async-timeout (==4.0.3)
Requires-Dist: asyncio (==3.4.3)
Requires-Dist: asynctest (==0.13.0)
Requires-Dist: attrs (==23.1.0)
Requires-Dist: beautifulsoup4 (==4.12.2)
Requires-Dist: certifi (==2023.7.22)
Requires-Dist: charset-normalizer (==3.2.0)
Requires-Dist: coverage (==7.3.2)
Requires-Dist: et-xmlfile (==1.1.0)
Requires-Dist: frozenlist (==1.4.0)
Requires-Dist: idna (==3.4)
Requires-Dist: multidict (==6.0.4)
Requires-Dist: numpy (==1.26.0)
Requires-Dist: openpyxl (==3.1.2)
Requires-Dist: pandas (==2.1.1)
Requires-Dist: python-dateutil (==2.8.2)
Requires-Dist: python-dotenv (==1.0.0)
Requires-Dist: pytz (==2023.3.post1)
Requires-Dist: requests (==2.31.0)
Requires-Dist: six (==1.16.0)
Requires-Dist: soupsieve (==2.5)
Requires-Dist: tzdata (==2023.3)
Requires-Dist: urllib3 (==2.0.6)
Requires-Dist: xlsxwriter (==3.1.5)
Requires-Dist: yarl (==1.9.2)
